README.md
setup.cfg
setup.py
diematic_client/__init__.py
diematic_client/__version__.py
diematic_client/boiler.py
diematic_client/enums.py
diematic_client/exceptions.py
diematic_client/models.py
diematic_client.egg-info/PKG-INFO
diematic_client.egg-info/SOURCES.txt
diematic_client.egg-info/dependency_links.txt
diematic_client.egg-info/requires.txt
diematic_client.egg-info/top_level.txt