Metadata-Version: 2.1
Name: diematic-client
Version: 1.5
Summary: Asynchronous Python client for diematic-server HTTP server
Home-page: https://github.com/IgnacioHR/diematic_client
Author: Ignacio Hernández-Ros
Author-email: ignacio@hernandez-ros.com
License: LGPL
Download-URL: https://github.com/IgnacioHR/diematic_client/archive/refs/tags/v1.5-beta.tar.gz
Keywords: python,home-automation,iot,restful,de-dietrich,diematic,home-assistant
Platform: UNKNOWN
Classifier: Development Status :: 4 - Beta
Classifier: Environment :: Plugins
Classifier: Intended Audience :: Developers
Classifier: License :: OSI Approved :: GNU Library or Lesser General Public License (LGPL)
Classifier: Operating System :: OS Independent
Classifier: Programming Language :: Python :: 3.7
Classifier: Topic :: Home Automation
